ophac_cpp.cp310-win32.pyd
ophac/__init__.py
ophac/_version.py
ophac/args.py
ophac/dendrogram.py
ophac/dtypes.py
ophac/hac.py
ophac/hac_approx.py
ophac/hierarchy.py
ophac/json_support.py
ophac/rnd.py
ophac/ultrametric.py
ophac-0.5.4.dist-info/licenses/LICENSE
ophac-0.5.4.dist-info/licenses/license_notice_header.txt
ophac-0.5.4.dist-info/METADATA
ophac-0.5.4.dist-info/WHEEL
ophac-0.5.4.dist-info/top_level.txt
ophac-0.5.4.dist-info/RECORD
