Metadata-Version: 2.4
Name: ophac
Version: 0.5.4
Summary: Order Preserving Hierarchical Agglomerative Clustering
Author-email: Daniel Bakkelund <daniel_bakkelund@hotmail.com>
License:                    GNU LESSER GENERAL PUBLIC LICENSE
Classifier: Programming Language :: Python :: 3
Classifier: License :: OSI Approved :: GNU Lesser General Public License v3 or later (LGPLv3+)
Classifier: Development Status :: 3 - Alpha
Classifier: Operating System :: OS Independent
Requires-Python: >=3.10
License-File: LICENSE
Requires-Dist: numpy
Provides-Extra: plot
Requires-Dist: scipy>=1.10; extra == "plot"
Dynamic: license-file
